perceptor/__init__.py
perceptor/drawers/__init__.py
perceptor/drawers/deep_image_prior.py
perceptor/drawers/diffusion/__init__.py
perceptor/drawers/diffusion/brute_diffusion.py
perceptor/drawers/diffusion/utils.py
perceptor/drawers/interface.py
perceptor/drawers/jpeg/__init__.py
perceptor/drawers/jpeg/compression.py
perceptor/drawers/jpeg/decompression.py
perceptor/drawers/jpeg/jpeg.py
perceptor/drawers/jpeg/utils.py
perceptor/drawers/raw/__init__.py
perceptor/drawers/raw/init/__init__.py
perceptor/drawers/raw/init/fractal.py
perceptor/drawers/raw/init/gradient.py
perceptor/drawers/raw/raw.py
perceptor/drawers/rudalle/__init__.py
perceptor/drawers/rudalle/brute_rudalle.py
perceptor/drawers/rudalle/decoder_dwt.py
perceptor/drawers/rudalle/get_vae.py
perceptor/drawers/rudalle/model.py
perceptor/drawers/rudalle/pytorch_wavelets_utils.py
perceptor/drawers/rudalle/vqgan.gumbelf8-sber.config.yml
perceptor/drawers/stylegan_xl.py
perceptor/losses/__init__.py
perceptor/losses/aesthetic_visual_assessment.py
perceptor/losses/blip.py
perceptor/losses/clip/__init__.py
perceptor/losses/clip/clip.py
perceptor/losses/clip/vectors/textoff.json
perceptor/losses/cloob.py
perceptor/losses/interface.py
perceptor/losses/lit.py
perceptor/losses/lpips.py
perceptor/losses/memorability.py
perceptor/losses/open_clip.py
perceptor/losses/owlvit.py
perceptor/losses/resize.py
perceptor/losses/ruclip.py
perceptor/losses/simulacra_aesthetic.py
perceptor/losses/slip.py
perceptor/losses/smoothness.py
perceptor/losses/spherical_distance.py
perceptor/losses/style_transfer.py
perceptor/losses/super_resolution/__init__.py
perceptor/losses/super_resolution/discriminator.py
perceptor/losses/super_resolution/super_resolution.py
perceptor/losses/super_resolution/unet_discriminator_sn.py
perceptor/losses/velocity_diffusion.py
perceptor/models/__init__.py
perceptor/models/adabins_depth/LICENSE
perceptor/models/adabins_depth/__init__.py
perceptor/models/adabins_depth/adabins_depth.py
perceptor-0.6.7.dist-info/LICENSE
perceptor-0.6.7.dist-info/WHEEL
perceptor-0.6.7.dist-info/METADATA
perceptor-0.6.7.dist-info/RECORD
