Metadata-Version: 2.1
Name: perceptor
Version: 0.6.7
Summary: Modular image generation library
Home-page: https://github.com/samedii/perceptor
Author: Richard Löwenström
Author-email: samedii@gmail.com
Requires-Python: >=3.8,<4.0
Classifier: Programming Language :: Python :: 3
Classifier: Programming Language :: Python :: 3.8
Classifier: Programming Language :: Python :: 3.9
Classifier: Programming Language :: Python :: 3.10
Requires-Dist: Pillow (>=9.0.1,<10.0.0)
Requires-Dist: basicsr (>=1.4.2,<2.0.0)
Requires-Dist: diffusers (>=0.6.0,<0.7.0)
Requires-Dist: dill (>=0.3.4,<0.4.0)
Requires-Dist: einops (>=0.4.0,<0.5.0)
Requires-Dist: ftfy (>=6.0.3,<7.0.0)
Requires-Dist: imageio (>=2.14.1,<3.0.0)
Requires-Dist: kornia (>=0.6.3,<0.7.0)
Requires-Dist: lpips (>=0.1.4,<0.2.0)
Requires-Dist: more-itertools (>=8.12.0,<9.0.0)
Requires-Dist: ninja (>=1.10.2,<2.0.0)
Requires-Dist: numpy (>=1.22.2,<2.0.0)
Requires-Dist: omegaconf (>=2.1.1,<3.0.0)
Requires-Dist: open-clip-torch (>=2.0.2,<3.0.0)
Requires-Dist: opencv-python (>=4.5.4,<5.0.0,!=4.6.0.66)
Requires-Dist: pytorch-lantern (>=0.12.0,<0.13.0)
Requires-Dist: pytorch-zero-lit (>=0.2.2,<0.3.0)
Requires-Dist: resmem (>=1.1.4,<2.0.0)
Requires-Dist: taming-transformers-rom1504 (>=0.0.6,<0.0.7)
Requires-Dist: timm (>=0.5.4,<0.6.0)
Requires-Dist: torch (>=1.12.1,<2.0.0)
Requires-Dist: torchvision
Requires-Dist: tqdm (>=4.62.3,<5.0.0)
Requires-Dist: transformers (>=4.21.1,<5.0.0)
Requires-Dist: triton (>=1.1.1,<2.0.0)
Requires-Dist: xformers (>=0.0.13,<0.0.14)
Requires-Dist: youtokentome (>=1.0.6,<2.0.0)
Project-URL: Repository, https://github.com/samedii/perceptor
